Metadata-Version: 2.1
Name: toggl2webcal
Version: 1.0
Summary: Export toggl to webcal file - uses sql database to store toggl data to get around API limits 
Home-page: https://github.com/visgean/toggl2webcal
Author: Visgean
Author-email: visgean@gmail.com
License: MIT
Keywords: toggl webcal
Platform: UNKNOWN
Classifier: License :: OSI Approved :: MIT License
Classifier: Programming Language :: Python :: 3
Classifier: Programming Language :: Python :: 3.7
